s2stools/__init__.py
s2stools/_version.py
s2stools/clim.py
s2stools/compute.py
s2stools/events.py
s2stools/indices.py
s2stools/plot.py
s2stools/process.py
s2stools/utils.py
s2stools/download/S2SDownloader.py
s2stools/download/__init__.py
s2stools/download/utils.py
s2stools/download/ecmwf/S2SDownloaderECMWF.py
s2stools/download/ecmwf/__init__.py
s2stools/download/ecmwf/model_setup.py
s2stools-0.4.1.dist-info/AUTHORS.rst
s2stools-0.4.1.dist-info/LICENSE
s2stools-0.4.1.dist-info/METADATA
s2stools-0.4.1.dist-info/WHEEL
s2stools-0.4.1.dist-info/top_level.txt
s2stools-0.4.1.dist-info/RECORD
