Metadata-Version: 2.1
Name: s2stools
Version: 0.4.1
Summary: Tools for working with s2s forecast data
Author-email: Jonas Spaeth <jonas.spaeth@physik.uni-muenchen.de>
License: BSD-3-Clause
Project-URL: Source Code, https://github.com/jonas-spaeth/s2stools
Project-URL: Bug Tracker, https://github.com/jonas-spaeth/s2stools/issues
Keywords: atmosphere,weather,climate
Classifier: Development Status :: 3 - Alpha
Classifier: Programming Language :: Python :: 3
Classifier: Topic :: Scientific/Engineering
Classifier: Topic :: Scientific/Engineering :: Atmospheric Science
Classifier: Intended Audience :: Science/Research
Requires-Python: >=3.8
License-File: LICENSE
License-File: AUTHORS.rst
Requires-Dist: numpy
Requires-Dist: scipy
Requires-Dist: xarray
Requires-Dist: tqdm
Requires-Dist: matplotlib
Requires-Dist: pandas
Requires-Dist: dask
Requires-Dist: ecmwf-api-client
